MonsterGen/__init__.py
MonsterGen/monster.py
MonsterGen/monster_lib.py
MonsterGen/monster_manual.py
MonsterGen/npc.py
MonsterGen/npc_lib.py
MonsterGen/spells.py
MonsterGen/traps.py
MonsterGen/treasure.py
MonsterGen-0.0.7.dist-info/LICENSE
MonsterGen-0.0.7.dist-info/METADATA
MonsterGen-0.0.7.dist-info/WHEEL
MonsterGen-0.0.7.dist-info/top_level.txt
MonsterGen-0.0.7.dist-info/RECORD
