Metadata-Version: 2.1
Name: MonsterGen
Version: 0.0.7
Summary: Random Monster Generator
Home-page: UNKNOWN
Author: Robert Sharp
Author-email: webmaster@sharpdesigndigital.com
License: UNKNOWN
Keywords: D&D,Monster,Trap,Treasure,NPC,Loot,Generator
Platform: UNKNOWN
Classifier: Development Status :: 4 - Beta
Classifier: Programming Language :: Python :: 3.8
Requires-Python: >=3.6
Requires-Dist: Fortuna
